__init__.py
apps.py
endpoint.py
exception_handler.py
fields.py
helper.py
registration.py
response.py
settings.py
tests.py
view.py
enum/__init__.py
enum/method.py
errors/BaseException.py
errors/EndpointException.py
errors/ForbiddenException.py
errors/MethodException.py
errors/WrongTypeException.py
errors/__init__.py
permissions/__init__.py
permissions/permissions.py
permissions/roles.py
myndress_django-0.0.1.dist-info/METADATA
myndress_django-0.0.1.dist-info/WHEEL
myndress_django-0.0.1.dist-info/top_level.txt
myndress_django-0.0.1.dist-info/RECORD
